reshell.py
reshell-1.1.1.dist-info/AUTHORS.rst
reshell-1.1.1.dist-info/LICENSE
reshell-1.1.1.dist-info/METADATA
reshell-1.1.1.dist-info/WHEEL
reshell-1.1.1.dist-info/entry_points.txt
reshell-1.1.1.dist-info/top_level.txt
reshell-1.1.1.dist-info/RECORD
