Metadata-Version: 2.1
Name: reshell
Version: 1.1.1
Summary: Python reverse bash shell
Home-page: https://github.com/peterdemin/reshell
Author: Peter Demin
Author-email: peterdemin@gmail.com
License: BSD
Keywords: reshell
Classifier: Development Status :: 6 - Mature
Classifier: Intended Audience :: Developers
Classifier: License :: OSI Approved :: BSD License
Classifier: Natural Language :: English
Classifier: Programming Language :: Python :: 3
Classifier: Programming Language :: Python :: 3.8
Classifier: Programming Language :: Python :: 3.9
Classifier: Programming Language :: Python :: 3.10
Classifier: Programming Language :: Python :: 3.11
Classifier: Programming Language :: Python :: 3.12
Classifier: Programming Language :: Python :: 3.13
Classifier: Programming Language :: Python :: 3.14
License-File: LICENSE
License-File: AUTHORS.rst
